awscloud.py
awscloud-0.0.1.dist-info/LICENSE.txt
awscloud-0.0.1.dist-info/METADATA
awscloud-0.0.1.dist-info/WHEEL
awscloud-0.0.1.dist-info/top_level.txt
awscloud-0.0.1.dist-info/RECORD
