Metadata-Version: 2.1
Name: awscloud
Version: 0.0.1
Summary: A Python Package to List AWS Cloud Resources for Different AWS Services!
Home-page: https://github.com/akashjeez/awscloud
Author: akashjeez
Author-email: akashit63@gmail.com
License: UNKNOWN
Platform: UNKNOWN
Classifier: Programming Language :: Python :: 3
Classifier: License :: OSI Approved :: MIT License
Classifier: Operating System :: OS Independent
Requires-Python: >=3.8
Requires-Dist: boto3
